dl_backtrace/__init__.py
dl_backtrace/version.py
dl_backtrace/pytorch_backtrace/__init__.py
dl_backtrace/pytorch_backtrace/backtrace/__init__.py
dl_backtrace/pytorch_backtrace/backtrace/backtrace.py
dl_backtrace/pytorch_backtrace/backtrace/config.py
dl_backtrace/pytorch_backtrace/backtrace/utils/__init__.py
dl_backtrace/pytorch_backtrace/backtrace/utils/contrast.py
dl_backtrace/pytorch_backtrace/backtrace/utils/prop.py
dl_backtrace/tf_backtrace/__init__.py
dl_backtrace/tf_backtrace/backtrace/__init__.py
dl_backtrace/tf_backtrace/backtrace/backtrace.py
dl_backtrace/tf_backtrace/backtrace/config.py
dl_backtrace/tf_backtrace/backtrace/utils/__init__.py
dl_backtrace/tf_backtrace/backtrace/utils/contrast.py
dl_backtrace/tf_backtrace/backtrace/utils/prop.py
dl_backtrace-0.2.dist-info/LICENSE
dl_backtrace-0.2.dist-info/METADATA
dl_backtrace-0.2.dist-info/WHEEL
dl_backtrace-0.2.dist-info/top_level.txt
dl_backtrace-0.2.dist-info/RECORD
