Metadata-Version: 2.1
Name: dl-backtrace
Version: 0.2
Summary: Add description here...
Home-page: https://xai.arya.ai/docs/introduction
License: MIT
Keywords: aryaxai,ML observability
Classifier: Intended Audience :: Developers
Classifier: Intended Audience :: Science/Research
Classifier: Programming Language :: Python :: 3
Classifier: License :: OSI Approved :: MIT License
Classifier: Operating System :: OS Independent
Requires-Python: >=3.0
License-File: LICENSE
Requires-Dist: tensorflow ==2.14.0
